{
  "timestamp": "2026-02-25T08:27:25.316992",
  "cycle": 5,
  "topology": "nominale",
  "migration_in_progress": false,
  "cpu_metrics": [
    {
      "name": "device-gf1-1-97f6bb7c7-bdtj8",
      "type": "device",
      "containers": [
        {
          "name": "device",
          "cpu_millicores": 0.833875,
          "cpu_raw": "833875n",
          "memory_mb": 17.81640625,
          "memory_raw": "18244Ki"
        },
        {
          "name": "istio-proxy",
          "cpu_millicores": 2.890028,
          "cpu_raw": "2890028n",
          "memory_mb": 37.92578125,
          "memory_raw": "38836Ki"
        }
      ]
    },
    {
      "name": "device-gf1-2-6dc5d7bc4-zjnmf",
      "type": "device",
      "containers": [
        {
          "name": "istio-proxy",
          "cpu_millicores": 3.251554,
          "cpu_raw": "3251554n",
          "memory_mb": 37.8671875,
          "memory_raw": "38776Ki"
        },
        {
          "name": "device",
          "cpu_millicores": 0.789589,
          "cpu_raw": "789589n",
          "memory_mb": 16.984375,
          "memory_raw": "17392Ki"
        }
      ]
    },
    {
      "name": "device-gf1-3-866965d5f5-mtfxh",
      "type": "device",
      "containers": [
        {
          "name": "device",
          "cpu_millicores": 0.687645,
          "cpu_raw": "687645n",
          "memory_mb": 17.19921875,
          "memory_raw": "17612Ki"
        },
        {
          "name": "istio-proxy",
          "cpu_millicores": 3.040896,
          "cpu_raw": "3040896n",
          "memory_mb": 36.80078125,
          "memory_raw": "37684Ki"
        }
      ]
    },
    {
      "name": "device-gf2-1-5c6cf686ff-ngg4c",
      "type": "device",
      "containers": [
        {
          "name": "device",
          "cpu_millicores": 0.733944,
          "cpu_raw": "733944n",
          "memory_mb": 17.30078125,
          "memory_raw": "17716Ki"
        },
        {
          "name": "istio-proxy",
          "cpu_millicores": 3.064953,
          "cpu_raw": "3064953n",
          "memory_mb": 36.3046875,
          "memory_raw": "37176Ki"
        }
      ]
    },
    {
      "name": "device-gf2-2-77f5f9b6cd-95bts",
      "type": "device",
      "containers": [
        {
          "name": "device",
          "cpu_millicores": 0.740509,
          "cpu_raw": "740509n",
          "memory_mb": 17.46484375,
          "memory_raw": "17884Ki"
        },
        {
          "name": "istio-proxy",
          "cpu_millicores": 3.285804,
          "cpu_raw": "3285804n",
          "memory_mb": 37.22265625,
          "memory_raw": "38116Ki"
        }
      ]
    },
    {
      "name": "device-gf2-3-76768476b9-pg8sk",
      "type": "device",
      "containers": [
        {
          "name": "istio-proxy",
          "cpu_millicores": 2.981059,
          "cpu_raw": "2981059n",
          "memory_mb": 36.78515625,
          "memory_raw": "37668Ki"
        },
        {
          "name": "device",
          "cpu_millicores": 0.768567,
          "cpu_raw": "768567n",
          "memory_mb": 17.1484375,
          "memory_raw": "17560Ki"
        }
      ]
    },
    {
      "name": "device-gf3-1-78c85cf677-d6dxs",
      "type": "device",
      "containers": [
        {
          "name": "istio-proxy",
          "cpu_millicores": 3.103299,
          "cpu_raw": "3103299n",
          "memory_mb": 37.83203125,
          "memory_raw": "38740Ki"
        },
        {
          "name": "device",
          "cpu_millicores": 0.594041,
          "cpu_raw": "594041n",
          "memory_mb": 23.24609375,
          "memory_raw": "23804Ki"
        }
      ]
    },
    {
      "name": "device-gf3-2-5774d89746-vvrjg",
      "type": "device",
      "containers": [
        {
          "name": "device",
          "cpu_millicores": 0.807185,
          "cpu_raw": "807185n",
          "memory_mb": 16.76953125,
          "memory_raw": "17172Ki"
        },
        {
          "name": "istio-proxy",
          "cpu_millicores": 3.008136,
          "cpu_raw": "3008136n",
          "memory_mb": 37.06640625,
          "memory_raw": "37956Ki"
        }
      ]
    },
    {
      "name": "device-gf3-3-6dc46955bc-xvkrm",
      "type": "device",
      "containers": [
        {
          "name": "device",
          "cpu_millicores": 0.862208,
          "cpu_raw": "862208n",
          "memory_mb": 17.25390625,
          "memory_raw": "17668Ki"
        },
        {
          "name": "istio-proxy",
          "cpu_millicores": 3.116186,
          "cpu_raw": "3116186n",
          "memory_mb": 38.12890625,
          "memory_raw": "39044Ki"
        }
      ]
    },
    {
      "name": "iot-application-zone1-79764bcb97-gd8j4",
      "type": "application",
      "containers": [
        {
          "name": "istio-proxy",
          "cpu_millicores": 2.950464,
          "cpu_raw": "2950464n",
          "memory_mb": 38.4296875,
          "memory_raw": "39352Ki"
        },
        {
          "name": "application",
          "cpu_millicores": 0.457517,
          "cpu_raw": "457517n",
          "memory_mb": 15.3046875,
          "memory_raw": "15672Ki"
        }
      ]
    },
    {
      "name": "iot-application-zone2-68f75455ff-zkz9n",
      "type": "application",
      "containers": [
        {
          "name": "application",
          "cpu_millicores": 0.35319,
          "cpu_raw": "353190n",
          "memory_mb": 17.10546875,
          "memory_raw": "17516Ki"
        },
        {
          "name": "istio-proxy",
          "cpu_millicores": 2.872967,
          "cpu_raw": "2872967n",
          "memory_mb": 37.703125,
          "memory_raw": "38608Ki"
        }
      ]
    },
    {
      "name": "iot-application-zone3-7c87cd9b77-qz4m2",
      "type": "application",
      "containers": [
        {
          "name": "application",
          "cpu_millicores": 0.359713,
          "cpu_raw": "359713n",
          "memory_mb": 16.375,
          "memory_raw": "16768Ki"
        },
        {
          "name": "istio-proxy",
          "cpu_millicores": 3.004618,
          "cpu_raw": "3004618n",
          "memory_mb": 37.90625,
          "memory_raw": "38816Ki"
        }
      ]
    },
    {
      "name": "iot-gateway-final-1-5c47ff88c5-bq4xh",
      "type": "gateway_finale",
      "containers": [
        {
          "name": "istio-proxy",
          "cpu_millicores": 4.484044,
          "cpu_raw": "4484044n",
          "memory_mb": 39.2109375,
          "memory_raw": "40152Ki"
        },
        {
          "name": "gateway",
          "cpu_millicores": 2.965089,
          "cpu_raw": "2965089n",
          "memory_mb": 33.85546875,
          "memory_raw": "34668Ki"
        }
      ]
    },
    {
      "name": "iot-gateway-final-2-c7884f86-4hqjx",
      "type": "gateway_finale",
      "containers": [
        {
          "name": "istio-proxy",
          "cpu_millicores": 4.483228,
          "cpu_raw": "4483228n",
          "memory_mb": 38.91796875,
          "memory_raw": "39852Ki"
        },
        {
          "name": "gateway",
          "cpu_millicores": 3.158786,
          "cpu_raw": "3158786n",
          "memory_mb": 29.18359375,
          "memory_raw": "29884Ki"
        }
      ]
    },
    {
      "name": "iot-gateway-final-3-54d4fc98c7-clts8",
      "type": "gateway_finale",
      "containers": [
        {
          "name": "istio-proxy",
          "cpu_millicores": 4.321306,
          "cpu_raw": "4321306n",
          "memory_mb": 39.23046875,
          "memory_raw": "40172Ki"
        },
        {
          "name": "gateway",
          "cpu_millicores": 2.747486,
          "cpu_raw": "2747486n",
          "memory_mb": 28.671875,
          "memory_raw": "29360Ki"
        }
      ]
    },
    {
      "name": "iot-gateway-inter-1-5959459d44-ktmbm",
      "type": "gateway_inter",
      "containers": [
        {
          "name": "gateway",
          "cpu_millicores": 7.086081,
          "cpu_raw": "7086081n",
          "memory_mb": 31.41015625,
          "memory_raw": "32164Ki"
        },
        {
          "name": "istio-proxy",
          "cpu_millicores": 7.161923,
          "cpu_raw": "7161923n",
          "memory_mb": 40.42578125,
          "memory_raw": "41396Ki"
        }
      ]
    },
    {
      "name": "iot-gateway-inter-2-79f8db59c6-9thkk",
      "type": "gateway_inter",
      "containers": [
        {
          "name": "gateway",
          "cpu_millicores": 0.003284,
          "cpu_raw": "3284n",
          "memory_mb": 14.71484375,
          "memory_raw": "15068Ki"
        },
        {
          "name": "istio-proxy",
          "cpu_millicores": 2.861732,
          "cpu_raw": "2861732n",
          "memory_mb": 37.12109375,
          "memory_raw": "38012Ki"
        }
      ]
    },
    {
      "name": "iot-server-6bcff59488-r6cn6",
      "type": "server",
      "containers": [
        {
          "name": "istio-proxy",
          "cpu_millicores": 5.224965,
          "cpu_raw": "5224965n",
          "memory_mb": 40.93359375,
          "memory_raw": "41916Ki"
        },
        {
          "name": "server",
          "cpu_millicores": 3.00972,
          "cpu_raw": "3009720n",
          "memory_mb": 39.0390625,
          "memory_raw": "39976Ki"
        }
      ]
    }
  ],
  "gateway_metrics": {
    "gateways_finales": {
      "iot-gateway-final-1": {
        "qps": 2.000096332684978,
        "qps_in": 0,
        "qps_out": 0,
        "latency_p95": 22.82263190254291,
        "bandwidth_in": 1304.9892330716366,
        "bandwidth_out": 1170.2734224275391,
        "error_rate": 0
      },
      "iot-gateway-final-2": {
        "qps": 1.9995487099038836,
        "qps_in": 0,
        "qps_out": 0,
        "latency_p95": 31.253744937083283,
        "bandwidth_in": 1304.9202559292637,
        "bandwidth_out": 1170.4080057282122,
        "error_rate": 0
      },
      "iot-gateway-final-3": {
        "qps": 1.9983577851781567,
        "qps_in": 0,
        "qps_out": 0,
        "latency_p95": 23.50028274609349,
        "bandwidth_in": 1303.5578875352244,
        "bandwidth_out": 1169.631091543519,
        "error_rate": 0
      }
    },
    "gateways_inter": {
      "iot-gateway-inter-1": {
        "qps": 5.9985794467502345,
        "qps_in": 0,
        "qps_out": 0,
        "latency_p95": 15.795925244997715,
        "bandwidth_in": 4244.5055586330245,
        "bandwidth_out": 3359.6796999001153,
        "error_rate": 0
      },
      "iot-gateway-inter-2": {
        "qps": 0,
        "qps_in": 0,
        "qps_out": 0,
        "latency_p95": 0,
        "bandwidth_in": 0,
        "bandwidth_out": 0.0,
        "error_rate": 0
      }
    }
  },
  "alerts": {
    "critical": [],
    "warning": []
  },
  "migration_triggered": false
}